[
  {
    "id": 1,
    "imgPath": "image.png",
    "title": "노트북 하나로 평생 돈 버는 <구글 온라인 자동화수익 만들기>",
    "tags": "창업 | 부업 | 선한부자 오가닉"
  },
  {
    "id": 2,
    "imgPath": "image-1.png",
    "title": "무명 이모티콘 작가가 인기 작가가 된 비결! 경쟁에서 살아남는 인기...",
    "tags": "디지털 드로잉 | 유랑"
  },
  {
    "id": 3,
    "imgPath": "image-2.png",
    "title": "미루는 습관을 없애줄 인생 관리 시스템",
    "tags": "라이프스타일 | 인생관리전문가 박소장"
  },
  {
    "id": 4,
    "imgPath": "image-3.png",
    "title": "크로키 찾아가는 나만의 선, 나만의 드로잉",
    "tags": "드로잉 | 조맹"
  },
  {
    "id": 5,
    "imgPath": "image-4.png",
    "title": "노트북 하나로 평생 돈 버는 <구글 온라인 자동화수익 만들기>",
    "tags": "창업 | 부업 | 선한부자 오가닉"
  },
  {
    "id": 6,
    "imgPath": "image-5.png",
    "title": "[2024년 개정판] 종이로 전하는 메세지, 토퍼 만들기부터 창업과...",
    "tags": "공예 | 밝음토퍼"
  }
]
